LICENSE
mdsdata/DS1_Iris/dataset.py
mdsdata/DS1_Iris/iris.csv
mdsdata/DS1_Iris/iris.names
mdsdata/DS2_Alpaydin_digits/dataset.py
mdsdata/DS2_Alpaydin_digits/optical+recognition+of+handwritten+digits/optdigits.names
mdsdata/DS2_Alpaydin_digits/optical+recognition+of+handwritten+digits/optdigits.tes
mdsdata/DS2_Alpaydin_digits/optical+recognition+of+handwritten+digits/optdigits.tra
mdsdata/DS2_Alpaydin_digits/optical+recognition+of+handwritten+digits/readme.txt
mdsdata/DS2_MNIST/data/t10k-images-idx3-ubyte.gz
mdsdata/DS2_MNIST/data/t10k-labels-idx1-ubyte.gz
mdsdata/DS2_MNIST/data/train-images-idx3-ubyte.gz
mdsdata/DS2_MNIST/data/train-labels-idx1-ubyte.gz
mdsdata/DS2_MNIST/dataset.py
mdsdata/MDS1_tensile_test/compute_strain_temperature_stress_data.py
mdsdata/MDS1_tensile_test/dataset.py
mdsdata/MDS1_tensile_test/strain.csv
mdsdata/MDS1_tensile_test/stress.csv
mdsdata/MDS1_tensile_test/write_csv_files.py
mdsdata/MDS2_Ising_model/dataset.py
mdsdata/MDS2_Ising_model/images_64.zip
mdsdata/MDS2_Ising_model/labels_64.csv
mdsdata/MDS2_Ising_model_light/dataset.py
mdsdata/MDS2_Ising_model_light/images_16.zip
mdsdata/MDS2_Ising_model_light/labels_16.csv
mdsdata/MDS3_CahnHilliard/data/images_0.zip
mdsdata/MDS3_CahnHilliard/data/images_1.zip
mdsdata/MDS3_CahnHilliard/data/images_10.zip
mdsdata/MDS3_CahnHilliard/data/images_11.zip
mdsdata/MDS3_CahnHilliard/data/images_12.zip
mdsdata/MDS3_CahnHilliard/data/images_13.zip
mdsdata/MDS3_CahnHilliard/data/images_14.zip
mdsdata/MDS3_CahnHilliard/data/images_15.zip
mdsdata/MDS3_CahnHilliard/data/images_16.zip
mdsdata/MDS3_CahnHilliard/data/images_17.zip
mdsdata/MDS3_CahnHilliard/data/images_2.zip
mdsdata/MDS3_CahnHilliard/data/images_3.zip
mdsdata/MDS3_CahnHilliard/data/images_4.zip
mdsdata/MDS3_CahnHilliard/data/images_5.zip
mdsdata/MDS3_CahnHilliard/data/images_6.zip
mdsdata/MDS3_CahnHilliard/data/images_7.zip
mdsdata/MDS3_CahnHilliard/data/images_8.zip
mdsdata/MDS3_CahnHilliard/data/images_9.zip
mdsdata-0.1.4.dist-info/LICENSE
mdsdata-0.1.4.dist-info/METADATA
mdsdata-0.1.4.dist-info/WHEEL
mdsdata-0.1.4.dist-info/RECORD
